escargot/__init__.py
escargot/escargot.py
escargot/utils.py
escargot/coder/__init__.py
escargot/coder/coder.py
escargot/controller/__init__.py
escargot/controller/controller.py
escargot/cypher/__init__.py
escargot/cypher/memgraph.py
escargot/language_models/__init__.py
escargot/language_models/abstract_language_model.py
escargot/language_models/azuregpt.py
escargot/language_models/chatgpt.py
escargot/language_models/config_template.json
escargot/memory/__init__.py
escargot/memory/memory.py
escargot/multiagent/__init__.py
escargot/multiagent/multiagent_manager.py
escargot/multiagent/utils.py
escargot/operations/__init__.py
escargot/operations/graph_of_operations.py
escargot/operations/operations.py
escargot/operations/thought.py
escargot/operations/utils.py
escargot/parser/__init__.py
escargot/parser/parser.py
escargot/parser/utils.py
escargot/prompter/__init__.py
escargot/prompter/prompter.py
escargot/vector_db/__init__.py
escargot/vector_db/azure_embedding.py
escargot/vector_db/weaviate.py
escargot-0.0.3.dist-info/METADATA
escargot-0.0.3.dist-info/WHEEL
escargot-0.0.3.dist-info/licenses/LICENSE
escargot-0.0.3.dist-info/RECORD
