Metadata-Version: 2.4
Name: escargot
Version: 0.0.3
Summary: Python package for ESCARGOT that enables solving elaborate problems with LLMs and Knowledge Graphs
Project-URL: Homepage, https://github.com/EpistasisLab/escargot
Author-email: Nicholas Matsumoto <nicholas.matsumoto@csmc.edu>
License: MIT License
License-File: LICENSE
Classifier: Operating System :: OS Independent
Classifier: Programming Language :: Python :: 3
Requires-Python: >=3.9
Requires-Dist: backoff<3.0.0,>=2.2.1
Requires-Dist: chromadb>=0.5.5
Requires-Dist: dill>=0.3.8
Requires-Dist: gqlalchemy>=1.5.1
Requires-Dist: matplotlib>=3.9.1
Requires-Dist: numpy<2.0.0,>=1.24.3
Requires-Dist: openai<2.0.0,>=1.0.0
Requires-Dist: pandas<3.0.0,>=2.0.3
Requires-Dist: scikit-learn>=1.0.1
Requires-Dist: seaborn>=0.11.2
Requires-Dist: weaviate-client>=4.6.5
